py_mini_sh/__init__.py
py_mini_sh-0.1.6.dist-info/licenses/LICENSE.txt
py_mini_sh-0.1.6.dist-info/METADATA
py_mini_sh-0.1.6.dist-info/WHEEL
py_mini_sh-0.1.6.dist-info/top_level.txt
py_mini_sh-0.1.6.dist-info/RECORD
