Metadata-Version: 2.4
Name: py_mini_sh
Version: 0.1.6
Summary: Python Mini Shell
Home-page: 
Author: Luke Tunmer
Author-email: luke.tunmer@gmail.com
Classifier: Development Status :: 4 - Beta
Classifier: Environment :: Console
Classifier: Intended Audience :: Developers
Classifier: License :: OSI Approved :: MIT License
Classifier: Operating System :: Microsoft :: Windows
Classifier: Operating System :: POSIX :: Linux
Classifier: Programming Language :: Python
Classifier: Topic :: Software Development :: Build Tools
Classifier: Topic :: Utilities
License-File: LICENSE.txt
Provides-Extra: testing
Requires-Dist: pylint; extra == "testing"
Requires-Dist: pytest; extra == "testing"
Requires-Dist: pytest-cov; extra == "testing"
Requires-Dist: Sphinx; extra == "testing"
Requires-Dist: sphinx_rtd_theme; extra == "testing"
Requires-Dist: wheel; extra == "testing"
Requires-Dist: bumpversion; extra == "testing"
Requires-Dist: twine; extra == "testing"
Dynamic: author
Dynamic: author-email
Dynamic: classifier
Dynamic: description
Dynamic: license-file
Dynamic: provides-extra
Dynamic: summary
